uw_adsel/VERSION
uw_adsel/__init__.py
uw_adsel/adselazure_assign_dao.py
uw_adsel/adselazure_merge_dao.py
uw_adsel/dao.py
uw_adsel/exceptions.py
uw_adsel/models.py
uw_adsel/test.py
uw_adsel/utilities.py
uw_adsel/resources/adsel/file/api/v1/academicqtr
uw_adsel/resources/adsel/file/api/v1/activities
uw_adsel/resources/adsel/file/api/v1/activities?Page=2
uw_adsel/resources/adsel/file/api/v1/activities?assignmentType=major
uw_adsel/resources/adsel/file/api/v1/activities?netid=javerage
uw_adsel/resources/adsel/file/api/v1/activities?netid=javerage&systemKey=12345
uw_adsel/resources/adsel/file/api/v1/workspaces?workspaceId=12&username=javerage
uw_adsel/resources/adsel/file/api/v1/admin/majors
uw_adsel/resources/adsel/file/api/v1/admin/majorvalues
uw_adsel/resources/adsel/file/api/v1/admin/cohorts/20194
uw_adsel/resources/adsel/file/api/v1/admin/cohorts/20201/0
uw_adsel/resources/adsel/file/api/v1/admin/major/1
uw_adsel/resources/adsel/file/api/v1/admin/major/2
uw_adsel/resources/adsel/file/api/v1/applications/0/123/1
uw_adsel/resources/adsel/file/api/v1/applications/0/all/1
uw_adsel/resources/adsel/file/api/v1/applications/AdmissionSelectionId/0/1
uw_adsel/resources/adsel/file/api/v1/applications/SystemKeys/0/1
uw_adsel/resources/adsel/file/api/v1/assignments/departmentalDecision
uw_adsel/resources/adsel/file/api/v1/assignments/major
uw_adsel/resources/adsel/file/api/v1/assignments/purpleAndGold
uw_adsel/resources/adsel/file/api/v1/assignments/cohort/bulk
uw_adsel/resources/adsel/file/api/v1/cohorts/0
uw_adsel/resources/adsel/file/api/v1/cohorts/0?Page=2
uw_adsel/resources/adsel/file/api/v1/cohorts/0?workspaceId=1
uw_adsel/resources/adsel/file/api/v1/cohorts/1
uw_adsel/resources/adsel/file/api/v1/departmentaldecisions/GetWithCounts?academicQtrKeyId=0
uw_adsel/resources/adsel/file/api/v1/departmentaldecisions/GetWithCounts?academicQtrKeyId=0&workspaceId=1
uw_adsel/resources/adsel/file/api/v1/departmentaldecisions/GetWithCounts?academicQtrKeyId=1
uw_restclients_adsel-3.5.3.dist-info/licenses/LICENSE
uw_restclients_adsel-3.5.3.dist-info/METADATA
uw_restclients_adsel-3.5.3.dist-info/WHEEL
uw_restclients_adsel-3.5.3.dist-info/top_level.txt
uw_restclients_adsel-3.5.3.dist-info/RECORD
