Metadata-Version: 2.4
Name: UW-RestClients-AdSel
Version: 3.5.3
Summary: A library for connecting to the AdSel API at the University of Washington
Home-page: https://github.com/uw-it-aca/uw-restclients-adsel
Author: UW-IT AXDD
Author-email: aca-it@uw.edu
License: Apache License, Version 2.0
Classifier: Intended Audience :: Developers
Classifier: License :: OSI Approved :: Apache Software License
Classifier: Operating System :: OS Independent
Classifier: Programming Language :: Python
Classifier: Programming Language :: Python :: 3.6
License-File: LICENSE
Requires-Dist: UW-RestClients-Core<2.0,>1.0
Requires-Dist: mock
Requires-Dist: python-dateutil
Dynamic: author
Dynamic: author-email
Dynamic: classifier
Dynamic: description
Dynamic: home-page
Dynamic: license
Dynamic: license-file
Dynamic: requires-dist
Dynamic: summary
